ipycc/__init__.py
ipycc/_colors.py
ipycc/sketch.py
ipycc/turtle.py
ipycc-0.0.16.dist-info/METADATA
ipycc-0.0.16.dist-info/WHEEL
ipycc-0.0.16.dist-info/licenses/LICENSE
ipycc-0.0.16.dist-info/RECORD
