Metadata-Version: 2.4
Name: ipycc
Version: 0.0.16
Summary: A Python package for creative coding in Jupyter
Project-URL: Homepage, https://ipy.cc
Project-URL: Issues, https://github.com/nickmcintyre/ipycc/issues
Author-email: Nick McIntyre <nick@mcintyre.io>
License-Expression: LGPL-3.0-or-later
License-File: LICENSE
Keywords: Art,Jupyter,Math,Sketch,Turtle,Visualization,p5.js
Classifier: Development Status :: 3 - Alpha
Classifier: Intended Audience :: Developers
Classifier: Intended Audience :: Education
Classifier: Intended Audience :: Science/Research
Classifier: License :: OSI Approved :: GNU Lesser General Public License v3 (LGPLv3)
Classifier: Operating System :: OS Independent
Classifier: Programming Language :: Python :: 3
Classifier: Topic :: Artistic Software
Classifier: Topic :: Multimedia :: Graphics
Classifier: Topic :: Scientific/Engineering :: Mathematics
Classifier: Topic :: Scientific/Engineering :: Visualization
Requires-Python: >=3.13
Requires-Dist: ipycanvas>=0.14.1
